fntom/CompressedFile.py
fntom/Constants.py
fntom/Counter.py
fntom/Error.py
fntom/FNTOMonoid.py
fntom/LevelEquivalence.py
fntom/Utils.py
fntom/__init__.py
fntom-0.2.0.dist-info/LICENSE
fntom-0.2.0.dist-info/METADATA
fntom-0.2.0.dist-info/WHEEL
fntom-0.2.0.dist-info/top_level.txt
fntom-0.2.0.dist-info/RECORD
