Metadata-Version: 2.1
Name: fntom
Version: 0.2.0
Summary: Implements a finite, negative, totally ordered monoid together with methods to compute its one-element Rees coextensions
Home-page: https://gitlab.com/petrikm/fntom
Author: Milan Petrík
Author-email: milan.petrik@protonmail.com
License: GPLv3
Keywords: discrete triangular norm,finite negative totally ordered monoid,Rees coextension,Rees congruence,Reidemeister closure condition,tomonoid partition
Platform: UNKNOWN
Classifier: Development Status :: 3 - Alpha
Classifier: Programming Language :: Python :: 3
Classifier: License :: OSI Approved :: GNU General Public License v3 (GPLv3)
Classifier: Operating System :: OS Independent
Classifier: Topic :: Scientific/Engineering :: Mathematics
Classifier: Intended Audience :: Science/Research
Requires-Python: >=3.6
